{
    "synthA": {
        "oscillator": {
        "type": "fmsquare",
        "modulationType": "sawtooth",
        "modulationIndex": 3,
        "harmonicity": 3.4
        },
        "envelope": {
        "attack": 0.001,
        "decay": 0.1,
        "sustain": 0.1,
        "release": 0.1
        }
    },

    "synthB" : {
        "oscillator": {
          "type": "triangle8"
        },
        "envelope": {
          "attack": 2,
          "decay": 1,
          "sustain": 0.4,
          "release": 4
        }
    },

    "cymbals" : {
        "volume": -20,
        "frequency"  : 100 ,
        "envelope"  : {
        "attack"  : 0.0001 ,
        "decay"  : 1.4 ,
        "release"  : 0.2
        }  ,
        "harmonicity"  : 5.1 ,
        "modulationIndex"  : 32 ,
        "resonance"  : 1000 ,
        "octaves"  : 1
    }
}